{
  "by_edge_status": {
    "MODERATE_EDGE": {
      "10d": {
        "close_call_primary_closer_rate": null,
        "close_call_sample_count": 0,
        "completed_count": 8,
        "primary_closer_than_secondary_rate": 0.75,
        "primary_path_mean_absolute_error": 0.008941,
        "primary_path_median_absolute_error": 0.006645,
        "primary_scenario_hit_rate": 0.25,
        "primary_vs_secondary_accuracy_spread": 0.0,
        "sample_gate": "insufficient_samples",
        "secondary_scenario_hit_rate": 0.25
      },
      "1d": {
        "close_call_primary_closer_rate": 0.5,
        "close_call_sample_count": 8,
        "completed_count": 25,
        "primary_closer_than_secondary_rate": 0.48,
        "primary_path_mean_absolute_error": 0.012417,
        "primary_path_median_absolute_error": 0.00726,
        "primary_scenario_hit_rate": 0.44,
        "primary_vs_secondary_accuracy_spread": 0.16,
        "sample_gate": "early_evidence",
        "secondary_scenario_hit_rate": 0.28
      },
      "20d": {
        "close_call_primary_closer_rate": null,
        "close_call_sample_count": 0,
        "completed_count": 0,
        "primary_closer_than_secondary_rate": null,
        "primary_path_mean_absolute_error": null,
        "primary_path_median_absolute_error": null,
        "primary_scenario_hit_rate": null,
        "primary_vs_secondary_accuracy_spread": null,
        "sample_gate": "insufficient_samples",
        "secondary_scenario_hit_rate": null
      },
      "3d": {
        "close_call_primary_closer_rate": 0.5,
        "close_call_sample_count": 6,
        "completed_count": 23,
        "primary_closer_than_secondary_rate": 0.2609,
        "primary_path_mean_absolute_error": 0.013876,
        "primary_path_median_absolute_error": 0.012787,
        "primary_scenario_hit_rate": 0.1739,
        "primary_vs_secondary_accuracy_spread": -0.2174,
        "sample_gate": "early_evidence",
        "secondary_scenario_hit_rate": 0.3913
      },
      "5d": {
        "close_call_primary_closer_rate": 0.6667,
        "close_call_sample_count": 3,
        "completed_count": 20,
        "primary_closer_than_secondary_rate": 0.6,
        "primary_path_mean_absolute_error": 0.015356,
        "primary_path_median_absolute_error": 0.00849,
        "primary_scenario_hit_rate": 0.45,
        "primary_vs_secondary_accuracy_spread": 0.35,
        "sample_gate": "early_evidence",
        "secondary_scenario_hit_rate": 0.1
      },
      "60d": {
        "close_call_primary_closer_rate": null,
        "close_call_sample_count": 0,
        "completed_count": 0,
        "primary_closer_than_secondary_rate": null,
        "primary_path_mean_absolute_error": null,
        "primary_path_median_absolute_error": null,
        "primary_scenario_hit_rate": null,
        "primary_vs_secondary_accuracy_spread": null,
        "sample_gate": "insufficient_samples",
        "secondary_scenario_hit_rate": null
      }
    },
    "RISK_WARNING": {
      "10d": {
        "close_call_primary_closer_rate": null,
        "close_call_sample_count": 0,
        "completed_count": 0,
        "primary_closer_than_secondary_rate": null,
        "primary_path_mean_absolute_error": null,
        "primary_path_median_absolute_error": null,
        "primary_scenario_hit_rate": null,
        "primary_vs_secondary_accuracy_spread": null,
        "sample_gate": "insufficient_samples",
        "secondary_scenario_hit_rate": null
      },
      "1d": {
        "close_call_primary_closer_rate": 0.4286,
        "close_call_sample_count": 7,
        "completed_count": 12,
        "primary_closer_than_secondary_rate": 0.3333,
        "primary_path_mean_absolute_error": 0.01322,
        "primary_path_median_absolute_error": 0.012277,
        "primary_scenario_hit_rate": 0.25,
        "primary_vs_secondary_accuracy_spread": -0.0833,
        "sample_gate": "insufficient_samples",
        "secondary_scenario_hit_rate": 0.3333
      },
      "20d": {
        "close_call_primary_closer_rate": null,
        "close_call_sample_count": 0,
        "completed_count": 0,
        "primary_closer_than_secondary_rate": null,
        "primary_path_mean_absolute_error": null,
        "primary_path_median_absolute_error": null,
        "primary_scenario_hit_rate": null,
        "primary_vs_secondary_accuracy_spread": null,
        "sample_gate": "insufficient_samples",
        "secondary_scenario_hit_rate": null
      },
      "3d": {
        "close_call_primary_closer_rate": 0.7143,
        "close_call_sample_count": 7,
        "completed_count": 12,
        "primary_closer_than_secondary_rate": 0.5,
        "primary_path_mean_absolute_error": 0.011366,
        "primary_path_median_absolute_error": 0.010146,
        "primary_scenario_hit_rate": 0.3333,
        "primary_vs_secondary_accuracy_spread": 0.0833,
        "sample_gate": "insufficient_samples",
        "secondary_scenario_hit_rate": 0.25
      },
      "5d": {
        "close_call_primary_closer_rate": 1.0,
        "close_call_sample_count": 3,
        "completed_count": 8,
        "primary_closer_than_secondary_rate": 0.5,
        "primary_path_mean_absolute_error": 0.017983,
        "primary_path_median_absolute_error": 0.017055,
        "primary_scenario_hit_rate": 0.25,
        "primary_vs_secondary_accuracy_spread": 0.0,
        "sample_gate": "insufficient_samples",
        "secondary_scenario_hit_rate": 0.25
      },
      "60d": {
        "close_call_primary_closer_rate": null,
        "close_call_sample_count": 0,
        "completed_count": 0,
        "primary_closer_than_secondary_rate": null,
        "primary_path_mean_absolute_error": null,
        "primary_path_median_absolute_error": null,
        "primary_scenario_hit_rate": null,
        "primary_vs_secondary_accuracy_spread": null,
        "sample_gate": "insufficient_samples",
        "secondary_scenario_hit_rate": null
      }
    },
    "STRONG_EDGE": {
      "10d": {
        "close_call_primary_closer_rate": null,
        "close_call_sample_count": 0,
        "completed_count": 0,
        "primary_closer_than_secondary_rate": null,
        "primary_path_mean_absolute_error": null,
        "primary_path_median_absolute_error": null,
        "primary_scenario_hit_rate": null,
        "primary_vs_secondary_accuracy_spread": null,
        "sample_gate": "insufficient_samples",
        "secondary_scenario_hit_rate": null
      },
      "1d": {
        "close_call_primary_closer_rate": 0.6667,
        "close_call_sample_count": 6,
        "completed_count": 6,
        "primary_closer_than_secondary_rate": 0.6667,
        "primary_path_mean_absolute_error": 0.009641,
        "primary_path_median_absolute_error": 0.008875,
        "primary_scenario_hit_rate": 0.3333,
        "primary_vs_secondary_accuracy_spread": 0.1667,
        "sample_gate": "insufficient_samples",
        "secondary_scenario_hit_rate": 0.1667
      },
      "20d": {
        "close_call_primary_closer_rate": null,
        "close_call_sample_count": 0,
        "completed_count": 0,
        "primary_closer_than_secondary_rate": null,
        "primary_path_mean_absolute_error": null,
        "primary_path_median_absolute_error": null,
        "primary_scenario_hit_rate": null,
        "primary_vs_secondary_accuracy_spread": null,
        "sample_gate": "insufficient_samples",
        "secondary_scenario_hit_rate": null
      },
      "3d": {
        "close_call_primary_closer_rate": 1.0,
        "close_call_sample_count": 1,
        "completed_count": 1,
        "primary_closer_than_secondary_rate": 1.0,
        "primary_path_mean_absolute_error": 0.000161,
        "primary_path_median_absolute_error": 0.000161,
        "primary_scenario_hit_rate": 1.0,
        "primary_vs_secondary_accuracy_spread": 1.0,
        "sample_gate": "insufficient_samples",
        "secondary_scenario_hit_rate": 0.0
      },
      "5d": {
        "close_call_primary_closer_rate": null,
        "close_call_sample_count": 0,
        "completed_count": 0,
        "primary_closer_than_secondary_rate": null,
        "primary_path_mean_absolute_error": null,
        "primary_path_median_absolute_error": null,
        "primary_scenario_hit_rate": null,
        "primary_vs_secondary_accuracy_spread": null,
        "sample_gate": "insufficient_samples",
        "secondary_scenario_hit_rate": null
      },
      "60d": {
        "close_call_primary_closer_rate": null,
        "close_call_sample_count": 0,
        "completed_count": 0,
        "primary_closer_than_secondary_rate": null,
        "primary_path_mean_absolute_error": null,
        "primary_path_median_absolute_error": null,
        "primary_scenario_hit_rate": null,
        "primary_vs_secondary_accuracy_spread": null,
        "sample_gate": "insufficient_samples",
        "secondary_scenario_hit_rate": null
      }
    },
    "WEAK_EDGE": {
      "10d": {
        "close_call_primary_closer_rate": null,
        "close_call_sample_count": 0,
        "completed_count": 0,
        "primary_closer_than_secondary_rate": null,
        "primary_path_mean_absolute_error": null,
        "primary_path_median_absolute_error": null,
        "primary_scenario_hit_rate": null,
        "primary_vs_secondary_accuracy_spread": null,
        "sample_gate": "insufficient_samples",
        "secondary_scenario_hit_rate": null
      },
      "1d": {
        "close_call_primary_closer_rate": null,
        "close_call_sample_count": 0,
        "completed_count": 1,
        "primary_closer_than_secondary_rate": 1.0,
        "primary_path_mean_absolute_error": 0.001941,
        "primary_path_median_absolute_error": 0.001941,
        "primary_scenario_hit_rate": 0.0,
        "primary_vs_secondary_accuracy_spread": 0.0,
        "sample_gate": "insufficient_samples",
        "secondary_scenario_hit_rate": 0.0
      },
      "20d": {
        "close_call_primary_closer_rate": null,
        "close_call_sample_count": 0,
        "completed_count": 0,
        "primary_closer_than_secondary_rate": null,
        "primary_path_mean_absolute_error": null,
        "primary_path_median_absolute_error": null,
        "primary_scenario_hit_rate": null,
        "primary_vs_secondary_accuracy_spread": null,
        "sample_gate": "insufficient_samples",
        "secondary_scenario_hit_rate": null
      },
      "3d": {
        "close_call_primary_closer_rate": null,
        "close_call_sample_count": 0,
        "completed_count": 0,
        "primary_closer_than_secondary_rate": null,
        "primary_path_mean_absolute_error": null,
        "primary_path_median_absolute_error": null,
        "primary_scenario_hit_rate": null,
        "primary_vs_secondary_accuracy_spread": null,
        "sample_gate": "insufficient_samples",
        "secondary_scenario_hit_rate": null
      },
      "5d": {
        "close_call_primary_closer_rate": null,
        "close_call_sample_count": 0,
        "completed_count": 0,
        "primary_closer_than_secondary_rate": null,
        "primary_path_mean_absolute_error": null,
        "primary_path_median_absolute_error": null,
        "primary_scenario_hit_rate": null,
        "primary_vs_secondary_accuracy_spread": null,
        "sample_gate": "insufficient_samples",
        "secondary_scenario_hit_rate": null
      },
      "60d": {
        "close_call_primary_closer_rate": null,
        "close_call_sample_count": 0,
        "completed_count": 0,
        "primary_closer_than_secondary_rate": null,
        "primary_path_mean_absolute_error": null,
        "primary_path_median_absolute_error": null,
        "primary_scenario_hit_rate": null,
        "primary_vs_secondary_accuracy_spread": null,
        "sample_gate": "insufficient_samples",
        "secondary_scenario_hit_rate": null
      }
    }
  },
  "by_scenario": {
    "bearish_path": {
      "10d": {
        "close_call_primary_closer_rate": null,
        "close_call_sample_count": 0,
        "completed_count": 0,
        "primary_closer_than_secondary_rate": null,
        "primary_path_mean_absolute_error": null,
        "primary_path_median_absolute_error": null,
        "primary_scenario_hit_rate": null,
        "primary_vs_secondary_accuracy_spread": null,
        "sample_gate": "insufficient_samples",
        "secondary_scenario_hit_rate": null
      },
      "1d": {
        "close_call_primary_closer_rate": 0.3333,
        "close_call_sample_count": 9,
        "completed_count": 11,
        "primary_closer_than_secondary_rate": 0.3636,
        "primary_path_mean_absolute_error": 0.01126,
        "primary_path_median_absolute_error": 0.010012,
        "primary_scenario_hit_rate": 0.1818,
        "primary_vs_secondary_accuracy_spread": -0.2727,
        "sample_gate": "insufficient_samples",
        "secondary_scenario_hit_rate": 0.4545
      },
      "20d": {
        "close_call_primary_closer_rate": null,
        "close_call_sample_count": 0,
        "completed_count": 0,
        "primary_closer_than_secondary_rate": null,
        "primary_path_mean_absolute_error": null,
        "primary_path_median_absolute_error": null,
        "primary_scenario_hit_rate": null,
        "primary_vs_secondary_accuracy_spread": null,
        "sample_gate": "insufficient_samples",
        "secondary_scenario_hit_rate": null
      },
      "3d": {
        "close_call_primary_closer_rate": 0.5,
        "close_call_sample_count": 8,
        "completed_count": 9,
        "primary_closer_than_secondary_rate": 0.4444,
        "primary_path_mean_absolute_error": 0.01555,
        "primary_path_median_absolute_error": 0.012094,
        "primary_scenario_hit_rate": 0.3333,
        "primary_vs_secondary_accuracy_spread": 0.0,
        "sample_gate": "insufficient_samples",
        "secondary_scenario_hit_rate": 0.3333
      },
      "5d": {
        "close_call_primary_closer_rate": 1.0,
        "close_call_sample_count": 3,
        "completed_count": 4,
        "primary_closer_than_secondary_rate": 0.75,
        "primary_path_mean_absolute_error": 0.018464,
        "primary_path_median_absolute_error": 0.01045,
        "primary_scenario_hit_rate": 0.5,
        "primary_vs_secondary_accuracy_spread": 0.25,
        "sample_gate": "insufficient_samples",
        "secondary_scenario_hit_rate": 0.25
      },
      "60d": {
        "close_call_primary_closer_rate": null,
        "close_call_sample_count": 0,
        "completed_count": 0,
        "primary_closer_than_secondary_rate": null,
        "primary_path_mean_absolute_error": null,
        "primary_path_median_absolute_error": null,
        "primary_scenario_hit_rate": null,
        "primary_vs_secondary_accuracy_spread": null,
        "sample_gate": "insufficient_samples",
        "secondary_scenario_hit_rate": null
      }
    },
    "bounce_path": {
      "10d": {
        "close_call_primary_closer_rate": null,
        "close_call_sample_count": 0,
        "completed_count": 8,
        "primary_closer_than_secondary_rate": 0.75,
        "primary_path_mean_absolute_error": 0.008941,
        "primary_path_median_absolute_error": 0.006645,
        "primary_scenario_hit_rate": 0.25,
        "primary_vs_secondary_accuracy_spread": 0.0,
        "sample_gate": "insufficient_samples",
        "secondary_scenario_hit_rate": 0.25
      },
      "1d": {
        "close_call_primary_closer_rate": 0.6667,
        "close_call_sample_count": 12,
        "completed_count": 33,
        "primary_closer_than_secondary_rate": 0.5152,
        "primary_path_mean_absolute_error": 0.012272,
        "primary_path_median_absolute_error": 0.010481,
        "primary_scenario_hit_rate": 0.4242,
        "primary_vs_secondary_accuracy_spread": 0.2121,
        "sample_gate": "early_evidence",
        "secondary_scenario_hit_rate": 0.2121
      },
      "20d": {
        "close_call_primary_closer_rate": null,
        "close_call_sample_count": 0,
        "completed_count": 0,
        "primary_closer_than_secondary_rate": null,
        "primary_path_mean_absolute_error": null,
        "primary_path_median_absolute_error": null,
        "primary_scenario_hit_rate": null,
        "primary_vs_secondary_accuracy_spread": null,
        "sample_gate": "insufficient_samples",
        "secondary_scenario_hit_rate": null
      },
      "3d": {
        "close_call_primary_closer_rate": 0.8333,
        "close_call_sample_count": 6,
        "completed_count": 27,
        "primary_closer_than_secondary_rate": 0.3333,
        "primary_path_mean_absolute_error": 0.011695,
        "primary_path_median_absolute_error": 0.010535,
        "primary_scenario_hit_rate": 0.2222,
        "primary_vs_secondary_accuracy_spread": -0.1111,
        "sample_gate": "early_evidence",
        "secondary_scenario_hit_rate": 0.3333
      },
      "5d": {
        "close_call_primary_closer_rate": 0.6667,
        "close_call_sample_count": 3,
        "completed_count": 24,
        "primary_closer_than_secondary_rate": 0.5417,
        "primary_path_mean_absolute_error": 0.015714,
        "primary_path_median_absolute_error": 0.00849,
        "primary_scenario_hit_rate": 0.375,
        "primary_vs_secondary_accuracy_spread": 0.25,
        "sample_gate": "early_evidence",
        "secondary_scenario_hit_rate": 0.125
      },
      "60d": {
        "close_call_primary_closer_rate": null,
        "close_call_sample_count": 0,
        "completed_count": 0,
        "primary_closer_than_secondary_rate": null,
        "primary_path_mean_absolute_error": null,
        "primary_path_median_absolute_error": null,
        "primary_scenario_hit_rate": null,
        "primary_vs_secondary_accuracy_spread": null,
        "sample_gate": "insufficient_samples",
        "secondary_scenario_hit_rate": null
      }
    }
  },
  "confidence_validation": {
    "breadth_confirmed": {
      "all": {
        "10d": {
          "close_call_primary_closer_rate": null,
          "close_call_sample_count": 0,
          "completed_count": 8,
          "primary_closer_than_secondary_rate": 0.75,
          "primary_path_mean_absolute_error": 0.008941,
          "primary_path_median_absolute_error": 0.006645,
          "primary_scenario_hit_rate": 0.25,
          "primary_vs_secondary_accuracy_spread": 0.0,
          "sample_gate": "insufficient_samples",
          "secondary_scenario_hit_rate": 0.25
        },
        "1d": {
          "close_call_primary_closer_rate": 0.625,
          "close_call_sample_count": 8,
          "completed_count": 28,
          "primary_closer_than_secondary_rate": 0.5,
          "primary_path_mean_absolute_error": 0.010588,
          "primary_path_median_absolute_error": 0.007189,
          "primary_scenario_hit_rate": 0.4643,
          "primary_vs_secondary_accuracy_spread": 0.2143,
          "sample_gate": "early_evidence",
          "secondary_scenario_hit_rate": 0.25
        },
        "20d": {
          "close_call_primary_closer_rate": null,
          "close_call_sample_count": 0,
          "completed_count": 0,
          "primary_closer_than_secondary_rate": null,
          "primary_path_mean_absolute_error": null,
          "primary_path_median_absolute_error": null,
          "primary_scenario_hit_rate": null,
          "primary_vs_secondary_accuracy_spread": null,
          "sample_gate": "insufficient_samples",
          "secondary_scenario_hit_rate": null
        },
        "3d": {
          "close_call_primary_closer_rate": 0.6667,
          "close_call_sample_count": 6,
          "completed_count": 26,
          "primary_closer_than_secondary_rate": 0.3077,
          "primary_path_mean_absolute_error": 0.011202,
          "primary_path_median_absolute_error": 0.010146,
          "primary_scenario_hit_rate": 0.1923,
          "primary_vs_secondary_accuracy_spread": -0.1923,
          "sample_gate": "early_evidence",
          "secondary_scenario_hit_rate": 0.3846
        },
        "5d": {
          "close_call_primary_closer_rate": 1.0,
          "close_call_sample_count": 2,
          "completed_count": 22,
          "primary_closer_than_secondary_rate": 0.5455,
          "primary_path_mean_absolute_error": 0.015917,
          "primary_path_median_absolute_error": 0.00849,
          "primary_scenario_hit_rate": 0.4091,
          "primary_vs_secondary_accuracy_spread": 0.2727,
          "sample_gate": "early_evidence",
          "secondary_scenario_hit_rate": 0.1364
        },
        "60d": {
          "close_call_primary_closer_rate": null,
          "close_call_sample_count": 0,
          "completed_count": 0,
          "primary_closer_than_secondary_rate": null,
          "primary_path_mean_absolute_error": null,
          "primary_path_median_absolute_error": null,
          "primary_scenario_hit_rate": null,
          "primary_vs_secondary_accuracy_spread": null,
          "sample_gate": "insufficient_samples",
          "secondary_scenario_hit_rate": null
        }
      }
    },
    "breadth_conflicted": {
      "all": {
        "10d": {
          "close_call_primary_closer_rate": null,
          "close_call_sample_count": 0,
          "completed_count": 0,
          "primary_closer_than_secondary_rate": null,
          "primary_path_mean_absolute_error": null,
          "primary_path_median_absolute_error": null,
          "primary_scenario_hit_rate": null,
          "primary_vs_secondary_accuracy_spread": null,
          "sample_gate": "insufficient_samples",
          "secondary_scenario_hit_rate": null
        },
        "1d": {
          "close_call_primary_closer_rate": 0.4,
          "close_call_sample_count": 15,
          "completed_count": 18,
          "primary_closer_than_secondary_rate": 0.3889,
          "primary_path_mean_absolute_error": 0.014241,
          "primary_path_median_absolute_error": 0.012255,
          "primary_scenario_hit_rate": 0.1667,
          "primary_vs_secondary_accuracy_spread": -0.2222,
          "sample_gate": "insufficient_samples",
          "secondary_scenario_hit_rate": 0.3889
        },
        "20d": {
          "close_call_primary_closer_rate": null,
          "close_call_sample_count": 0,
          "completed_count": 0,
          "primary_closer_than_secondary_rate": null,
          "primary_path_mean_absolute_error": null,
          "primary_path_median_absolute_error": null,
          "primary_scenario_hit_rate": null,
          "primary_vs_secondary_accuracy_spread": null,
          "sample_gate": "insufficient_samples",
          "secondary_scenario_hit_rate": null
        },
        "3d": {
          "close_call_primary_closer_rate": 0.5,
          "close_call_sample_count": 10,
          "completed_count": 12,
          "primary_closer_than_secondary_rate": 0.4167,
          "primary_path_mean_absolute_error": 0.01716,
          "primary_path_median_absolute_error": 0.016818,
          "primary_scenario_hit_rate": 0.3333,
          "primary_vs_secondary_accuracy_spread": 0.0,
          "sample_gate": "insufficient_samples",
          "secondary_scenario_hit_rate": 0.3333
        },
        "5d": {
          "close_call_primary_closer_rate": 0.75,
          "close_call_sample_count": 4,
          "completed_count": 6,
          "primary_closer_than_secondary_rate": 0.6667,
          "primary_path_mean_absolute_error": 0.016803,
          "primary_path_median_absolute_error": 0.01045,
          "primary_scenario_hit_rate": 0.3333,
          "primary_vs_secondary_accuracy_spread": 0.1667,
          "sample_gate": "insufficient_samples",
          "secondary_scenario_hit_rate": 0.1667
        },
        "60d": {
          "close_call_primary_closer_rate": null,
          "close_call_sample_count": 0,
          "completed_count": 0,
          "primary_closer_than_secondary_rate": null,
          "primary_path_mean_absolute_error": null,
          "primary_path_median_absolute_error": null,
          "primary_scenario_hit_rate": null,
          "primary_vs_secondary_accuracy_spread": null,
          "sample_gate": "insufficient_samples",
          "secondary_scenario_hit_rate": null
        }
      }
    },
    "confidence_top_10": {
      "all": {
        "10d": {
          "close_call_primary_closer_rate": null,
          "close_call_sample_count": 0,
          "completed_count": 1,
          "primary_closer_than_secondary_rate": 0.0,
          "primary_path_mean_absolute_error": 0.001725,
          "primary_path_median_absolute_error": 0.001725,
          "primary_scenario_hit_rate": 0.0,
          "primary_vs_secondary_accuracy_spread": -1.0,
          "sample_gate": "insufficient_samples",
          "secondary_scenario_hit_rate": 1.0
        },
        "1d": {
          "close_call_primary_closer_rate": null,
          "close_call_sample_count": 0,
          "completed_count": 4,
          "primary_closer_than_secondary_rate": 0.25,
          "primary_path_mean_absolute_error": 0.012507,
          "primary_path_median_absolute_error": 0.011378,
          "primary_scenario_hit_rate": 0.0,
          "primary_vs_secondary_accuracy_spread": -0.25,
          "sample_gate": "insufficient_samples",
          "secondary_scenario_hit_rate": 0.25
        },
        "20d": {
          "close_call_primary_closer_rate": null,
          "close_call_sample_count": 0,
          "completed_count": 0,
          "primary_closer_than_secondary_rate": null,
          "primary_path_mean_absolute_error": null,
          "primary_path_median_absolute_error": null,
          "primary_scenario_hit_rate": null,
          "primary_vs_secondary_accuracy_spread": null,
          "sample_gate": "insufficient_samples",
          "secondary_scenario_hit_rate": null
        },
        "3d": {
          "close_call_primary_closer_rate": null,
          "close_call_sample_count": 0,
          "completed_count": 4,
          "primary_closer_than_secondary_rate": 0.0,
          "primary_path_mean_absolute_error": 0.01337,
          "primary_path_median_absolute_error": 0.011442,
          "primary_scenario_hit_rate": 0.0,
          "primary_vs_secondary_accuracy_spread": -0.5,
          "sample_gate": "insufficient_samples",
          "secondary_scenario_hit_rate": 0.5
        },
        "5d": {
          "close_call_primary_closer_rate": null,
          "close_call_sample_count": 0,
          "completed_count": 4,
          "primary_closer_than_secondary_rate": 0.5,
          "primary_path_mean_absolute_error": 0.025137,
          "primary_path_median_absolute_error": 0.028046,
          "primary_scenario_hit_rate": 0.25,
          "primary_vs_secondary_accuracy_spread": 0.25,
          "sample_gate": "insufficient_samples",
          "secondary_scenario_hit_rate": 0.0
        },
        "60d": {
          "close_call_primary_closer_rate": null,
          "close_call_sample_count": 0,
          "completed_count": 0,
          "primary_closer_than_secondary_rate": null,
          "primary_path_mean_absolute_error": null,
          "primary_path_median_absolute_error": null,
          "primary_scenario_hit_rate": null,
          "primary_vs_secondary_accuracy_spread": null,
          "sample_gate": "insufficient_samples",
          "secondary_scenario_hit_rate": null
        }
      }
    },
    "flow_confirmed": {
      "all": {
        "10d": {
          "close_call_primary_closer_rate": null,
          "close_call_sample_count": 0,
          "completed_count": 8,
          "primary_closer_than_secondary_rate": 0.75,
          "primary_path_mean_absolute_error": 0.008941,
          "primary_path_median_absolute_error": 0.006645,
          "primary_scenario_hit_rate": 0.25,
          "primary_vs_secondary_accuracy_spread": 0.0,
          "sample_gate": "insufficient_samples",
          "secondary_scenario_hit_rate": 0.25
        },
        "1d": {
          "close_call_primary_closer_rate": 0.5263,
          "close_call_sample_count": 19,
          "completed_count": 42,
          "primary_closer_than_secondary_rate": 0.4762,
          "primary_path_mean_absolute_error": 0.012355,
          "primary_path_median_absolute_error": 0.010706,
          "primary_scenario_hit_rate": 0.381,
          "primary_vs_secondary_accuracy_spread": 0.119,
          "sample_gate": "early_evidence",
          "secondary_scenario_hit_rate": 0.2619
        },
        "20d": {
          "close_call_primary_closer_rate": null,
          "close_call_sample_count": 0,
          "completed_count": 0,
          "primary_closer_than_secondary_rate": null,
          "primary_path_mean_absolute_error": null,
          "primary_path_median_absolute_error": null,
          "primary_scenario_hit_rate": null,
          "primary_vs_secondary_accuracy_spread": null,
          "sample_gate": "insufficient_samples",
          "secondary_scenario_hit_rate": null
        },
        "3d": {
          "close_call_primary_closer_rate": 0.75,
          "close_call_sample_count": 12,
          "completed_count": 34,
          "primary_closer_than_secondary_rate": 0.3824,
          "primary_path_mean_absolute_error": 0.012289,
          "primary_path_median_absolute_error": 0.010146,
          "primary_scenario_hit_rate": 0.2647,
          "primary_vs_secondary_accuracy_spread": -0.0588,
          "sample_gate": "early_evidence",
          "secondary_scenario_hit_rate": 0.3235
        },
        "5d": {
          "close_call_primary_closer_rate": 0.8333,
          "close_call_sample_count": 6,
          "completed_count": 28,
          "primary_closer_than_secondary_rate": 0.5714,
          "primary_path_mean_absolute_error": 0.016107,
          "primary_path_median_absolute_error": 0.008924,
          "primary_scenario_hit_rate": 0.3929,
          "primary_vs_secondary_accuracy_spread": 0.25,
          "sample_gate": "early_evidence",
          "secondary_scenario_hit_rate": 0.1429
        },
        "60d": {
          "close_call_primary_closer_rate": null,
          "close_call_sample_count": 0,
          "completed_count": 0,
          "primary_closer_than_secondary_rate": null,
          "primary_path_mean_absolute_error": null,
          "primary_path_median_absolute_error": null,
          "primary_scenario_hit_rate": null,
          "primary_vs_secondary_accuracy_spread": null,
          "sample_gate": "insufficient_samples",
          "secondary_scenario_hit_rate": null
        }
      }
    },
    "flow_conflicted": {
      "all": {
        "10d": {
          "close_call_primary_closer_rate": null,
          "close_call_sample_count": 0,
          "completed_count": 0,
          "primary_closer_than_secondary_rate": null,
          "primary_path_mean_absolute_error": null,
          "primary_path_median_absolute_error": null,
          "primary_scenario_hit_rate": null,
          "primary_vs_secondary_accuracy_spread": null,
          "sample_gate": "insufficient_samples",
          "secondary_scenario_hit_rate": null
        },
        "1d": {
          "close_call_primary_closer_rate": null,
          "close_call_sample_count": 0,
          "completed_count": 0,
          "primary_closer_than_secondary_rate": null,
          "primary_path_mean_absolute_error": null,
          "primary_path_median_absolute_error": null,
          "primary_scenario_hit_rate": null,
          "primary_vs_secondary_accuracy_spread": null,
          "sample_gate": "insufficient_samples",
          "secondary_scenario_hit_rate": null
        },
        "20d": {
          "close_call_primary_closer_rate": null,
          "close_call_sample_count": 0,
          "completed_count": 0,
          "primary_closer_than_secondary_rate": null,
          "primary_path_mean_absolute_error": null,
          "primary_path_median_absolute_error": null,
          "primary_scenario_hit_rate": null,
          "primary_vs_secondary_accuracy_spread": null,
          "sample_gate": "insufficient_samples",
          "secondary_scenario_hit_rate": null
        },
        "3d": {
          "close_call_primary_closer_rate": null,
          "close_call_sample_count": 0,
          "completed_count": 0,
          "primary_closer_than_secondary_rate": null,
          "primary_path_mean_absolute_error": null,
          "primary_path_median_absolute_error": null,
          "primary_scenario_hit_rate": null,
          "primary_vs_secondary_accuracy_spread": null,
          "sample_gate": "insufficient_samples",
          "secondary_scenario_hit_rate": null
        },
        "5d": {
          "close_call_primary_closer_rate": null,
          "close_call_sample_count": 0,
          "completed_count": 0,
          "primary_closer_than_secondary_rate": null,
          "primary_path_mean_absolute_error": null,
          "primary_path_median_absolute_error": null,
          "primary_scenario_hit_rate": null,
          "primary_vs_secondary_accuracy_spread": null,
          "sample_gate": "insufficient_samples",
          "secondary_scenario_hit_rate": null
        },
        "60d": {
          "close_call_primary_closer_rate": null,
          "close_call_sample_count": 0,
          "completed_count": 0,
          "primary_closer_than_secondary_rate": null,
          "primary_path_mean_absolute_error": null,
          "primary_path_median_absolute_error": null,
          "primary_scenario_hit_rate": null,
          "primary_vs_secondary_accuracy_spread": null,
          "sample_gate": "insufficient_samples",
          "secondary_scenario_hit_rate": null
        }
      }
    },
    "high_data_completeness": {
      "all": {
        "10d": {
          "close_call_primary_closer_rate": null,
          "close_call_sample_count": 0,
          "completed_count": 8,
          "primary_closer_than_secondary_rate": 0.75,
          "primary_path_mean_absolute_error": 0.008941,
          "primary_path_median_absolute_error": 0.006645,
          "primary_scenario_hit_rate": 0.25,
          "primary_vs_secondary_accuracy_spread": 0.0,
          "sample_gate": "insufficient_samples",
          "secondary_scenario_hit_rate": 0.25
        },
        "1d": {
          "close_call_primary_closer_rate": 0.5238,
          "close_call_sample_count": 21,
          "completed_count": 44,
          "primary_closer_than_secondary_rate": 0.4773,
          "primary_path_mean_absolute_error": 0.012019,
          "primary_path_median_absolute_error": 0.010246,
          "primary_scenario_hit_rate": 0.3636,
          "primary_vs_secondary_accuracy_spread": 0.0909,
          "sample_gate": "early_evidence",
          "secondary_scenario_hit_rate": 0.2727
        },
        "20d": {
          "close_call_primary_closer_rate": null,
          "close_call_sample_count": 0,
          "completed_count": 0,
          "primary_closer_than_secondary_rate": null,
          "primary_path_mean_absolute_error": null,
          "primary_path_median_absolute_error": null,
          "primary_scenario_hit_rate": null,
          "primary_vs_secondary_accuracy_spread": null,
          "sample_gate": "insufficient_samples",
          "secondary_scenario_hit_rate": null
        },
        "3d": {
          "close_call_primary_closer_rate": 0.6429,
          "close_call_sample_count": 14,
          "completed_count": 36,
          "primary_closer_than_secondary_rate": 0.3611,
          "primary_path_mean_absolute_error": 0.012659,
          "primary_path_median_absolute_error": 0.011191,
          "primary_scenario_hit_rate": 0.25,
          "primary_vs_secondary_accuracy_spread": -0.0833,
          "sample_gate": "early_evidence",
          "secondary_scenario_hit_rate": 0.3333
        },
        "5d": {
          "close_call_primary_closer_rate": 0.8333,
          "close_call_sample_count": 6,
          "completed_count": 28,
          "primary_closer_than_secondary_rate": 0.5714,
          "primary_path_mean_absolute_error": 0.016107,
          "primary_path_median_absolute_error": 0.008924,
          "primary_scenario_hit_rate": 0.3929,
          "primary_vs_secondary_accuracy_spread": 0.25,
          "sample_gate": "early_evidence",
          "secondary_scenario_hit_rate": 0.1429
        },
        "60d": {
          "close_call_primary_closer_rate": null,
          "close_call_sample_count": 0,
          "completed_count": 0,
          "primary_closer_than_secondary_rate": null,
          "primary_path_mean_absolute_error": null,
          "primary_path_median_absolute_error": null,
          "primary_scenario_hit_rate": null,
          "primary_vs_secondary_accuracy_spread": null,
          "sample_gate": "insufficient_samples",
          "secondary_scenario_hit_rate": null
        }
      }
    },
    "low_data_completeness": {
      "all": {
        "10d": {
          "close_call_primary_closer_rate": null,
          "close_call_sample_count": 0,
          "completed_count": 0,
          "primary_closer_than_secondary_rate": null,
          "primary_path_mean_absolute_error": null,
          "primary_path_median_absolute_error": null,
          "primary_scenario_hit_rate": null,
          "primary_vs_secondary_accuracy_spread": null,
          "sample_gate": "insufficient_samples",
          "secondary_scenario_hit_rate": null
        },
        "1d": {
          "close_call_primary_closer_rate": null,
          "close_call_sample_count": 0,
          "completed_count": 0,
          "primary_closer_than_secondary_rate": null,
          "primary_path_mean_absolute_error": null,
          "primary_path_median_absolute_error": null,
          "primary_scenario_hit_rate": null,
          "primary_vs_secondary_accuracy_spread": null,
          "sample_gate": "insufficient_samples",
          "secondary_scenario_hit_rate": null
        },
        "20d": {
          "close_call_primary_closer_rate": null,
          "close_call_sample_count": 0,
          "completed_count": 0,
          "primary_closer_than_secondary_rate": null,
          "primary_path_mean_absolute_error": null,
          "primary_path_median_absolute_error": null,
          "primary_scenario_hit_rate": null,
          "primary_vs_secondary_accuracy_spread": null,
          "sample_gate": "insufficient_samples",
          "secondary_scenario_hit_rate": null
        },
        "3d": {
          "close_call_primary_closer_rate": null,
          "close_call_sample_count": 0,
          "completed_count": 0,
          "primary_closer_than_secondary_rate": null,
          "primary_path_mean_absolute_error": null,
          "primary_path_median_absolute_error": null,
          "primary_scenario_hit_rate": null,
          "primary_vs_secondary_accuracy_spread": null,
          "sample_gate": "insufficient_samples",
          "secondary_scenario_hit_rate": null
        },
        "5d": {
          "close_call_primary_closer_rate": null,
          "close_call_sample_count": 0,
          "completed_count": 0,
          "primary_closer_than_secondary_rate": null,
          "primary_path_mean_absolute_error": null,
          "primary_path_median_absolute_error": null,
          "primary_scenario_hit_rate": null,
          "primary_vs_secondary_accuracy_spread": null,
          "sample_gate": "insufficient_samples",
          "secondary_scenario_hit_rate": null
        },
        "60d": {
          "close_call_primary_closer_rate": null,
          "close_call_sample_count": 0,
          "completed_count": 0,
          "primary_closer_than_secondary_rate": null,
          "primary_path_mean_absolute_error": null,
          "primary_path_median_absolute_error": null,
          "primary_scenario_hit_rate": null,
          "primary_vs_secondary_accuracy_spread": null,
          "sample_gate": "insufficient_samples",
          "secondary_scenario_hit_rate": null
        }
      }
    },
    "options_confirmed": {
      "all": {
        "10d": {
          "close_call_primary_closer_rate": null,
          "close_call_sample_count": 0,
          "completed_count": 8,
          "primary_closer_than_secondary_rate": 0.75,
          "primary_path_mean_absolute_error": 0.008941,
          "primary_path_median_absolute_error": 0.006645,
          "primary_scenario_hit_rate": 0.25,
          "primary_vs_secondary_accuracy_spread": 0.0,
          "sample_gate": "insufficient_samples",
          "secondary_scenario_hit_rate": 0.25
        },
        "1d": {
          "close_call_primary_closer_rate": 0.6667,
          "close_call_sample_count": 6,
          "completed_count": 28,
          "primary_closer_than_secondary_rate": 0.4643,
          "primary_path_mean_absolute_error": 0.013858,
          "primary_path_median_absolute_error": 0.010793,
          "primary_scenario_hit_rate": 0.4286,
          "primary_vs_secondary_accuracy_spread": 0.2143,
          "sample_gate": "early_evidence",
          "secondary_scenario_hit_rate": 0.2143
        },
        "20d": {
          "close_call_primary_closer_rate": null,
          "close_call_sample_count": 0,
          "completed_count": 0,
          "primary_closer_than_secondary_rate": null,
          "primary_path_mean_absolute_error": null,
          "primary_path_median_absolute_error": null,
          "primary_scenario_hit_rate": null,
          "primary_vs_secondary_accuracy_spread": null,
          "sample_gate": "insufficient_samples",
          "secondary_scenario_hit_rate": null
        },
        "3d": {
          "close_call_primary_closer_rate": 1.0,
          "close_call_sample_count": 6,
          "completed_count": 28,
          "primary_closer_than_secondary_rate": 0.3571,
          "primary_path_mean_absolute_error": 0.012609,
          "primary_path_median_absolute_error": 0.010146,
          "primary_scenario_hit_rate": 0.2857,
          "primary_vs_secondary_accuracy_spread": -0.0357,
          "sample_gate": "early_evidence",
          "secondary_scenario_hit_rate": 0.3214
        },
        "5d": {
          "close_call_primary_closer_rate": 0.8333,
          "close_call_sample_count": 6,
          "completed_count": 28,
          "primary_closer_than_secondary_rate": 0.5714,
          "primary_path_mean_absolute_error": 0.016107,
          "primary_path_median_absolute_error": 0.008924,
          "primary_scenario_hit_rate": 0.3929,
          "primary_vs_secondary_accuracy_spread": 0.25,
          "sample_gate": "early_evidence",
          "secondary_scenario_hit_rate": 0.1429
        },
        "60d": {
          "close_call_primary_closer_rate": null,
          "close_call_sample_count": 0,
          "completed_count": 0,
          "primary_closer_than_secondary_rate": null,
          "primary_path_mean_absolute_error": null,
          "primary_path_median_absolute_error": null,
          "primary_scenario_hit_rate": null,
          "primary_vs_secondary_accuracy_spread": null,
          "sample_gate": "insufficient_samples",
          "secondary_scenario_hit_rate": null
        }
      }
    },
    "options_conflicted": {
      "all": {
        "10d": {
          "close_call_primary_closer_rate": null,
          "close_call_sample_count": 0,
          "completed_count": 0,
          "primary_closer_than_secondary_rate": null,
          "primary_path_mean_absolute_error": null,
          "primary_path_median_absolute_error": null,
          "primary_scenario_hit_rate": null,
          "primary_vs_secondary_accuracy_spread": null,
          "sample_gate": "insufficient_samples",
          "secondary_scenario_hit_rate": null
        },
        "1d": {
          "close_call_primary_closer_rate": null,
          "close_call_sample_count": 0,
          "completed_count": 0,
          "primary_closer_than_secondary_rate": null,
          "primary_path_mean_absolute_error": null,
          "primary_path_median_absolute_error": null,
          "primary_scenario_hit_rate": null,
          "primary_vs_secondary_accuracy_spread": null,
          "sample_gate": "insufficient_samples",
          "secondary_scenario_hit_rate": null
        },
        "20d": {
          "close_call_primary_closer_rate": null,
          "close_call_sample_count": 0,
          "completed_count": 0,
          "primary_closer_than_secondary_rate": null,
          "primary_path_mean_absolute_error": null,
          "primary_path_median_absolute_error": null,
          "primary_scenario_hit_rate": null,
          "primary_vs_secondary_accuracy_spread": null,
          "sample_gate": "insufficient_samples",
          "secondary_scenario_hit_rate": null
        },
        "3d": {
          "close_call_primary_closer_rate": null,
          "close_call_sample_count": 0,
          "completed_count": 0,
          "primary_closer_than_secondary_rate": null,
          "primary_path_mean_absolute_error": null,
          "primary_path_median_absolute_error": null,
          "primary_scenario_hit_rate": null,
          "primary_vs_secondary_accuracy_spread": null,
          "sample_gate": "insufficient_samples",
          "secondary_scenario_hit_rate": null
        },
        "5d": {
          "close_call_primary_closer_rate": null,
          "close_call_sample_count": 0,
          "completed_count": 0,
          "primary_closer_than_secondary_rate": null,
          "primary_path_mean_absolute_error": null,
          "primary_path_median_absolute_error": null,
          "primary_scenario_hit_rate": null,
          "primary_vs_secondary_accuracy_spread": null,
          "sample_gate": "insufficient_samples",
          "secondary_scenario_hit_rate": null
        },
        "60d": {
          "close_call_primary_closer_rate": null,
          "close_call_sample_count": 0,
          "completed_count": 0,
          "primary_closer_than_secondary_rate": null,
          "primary_path_mean_absolute_error": null,
          "primary_path_median_absolute_error": null,
          "primary_scenario_hit_rate": null,
          "primary_vs_secondary_accuracy_spread": null,
          "sample_gate": "insufficient_samples",
          "secondary_scenario_hit_rate": null
        }
      }
    },
    "signal_confirmation_top_10": {
      "all": {
        "10d": {
          "close_call_primary_closer_rate": null,
          "close_call_sample_count": 0,
          "completed_count": 1,
          "primary_closer_than_secondary_rate": 1.0,
          "primary_path_mean_absolute_error": 0.002156,
          "primary_path_median_absolute_error": 0.002156,
          "primary_scenario_hit_rate": 1.0,
          "primary_vs_secondary_accuracy_spread": 1.0,
          "sample_gate": "insufficient_samples",
          "secondary_scenario_hit_rate": 0.0
        },
        "1d": {
          "close_call_primary_closer_rate": 0.0,
          "close_call_sample_count": 1,
          "completed_count": 5,
          "primary_closer_than_secondary_rate": 0.2,
          "primary_path_mean_absolute_error": 0.020529,
          "primary_path_median_absolute_error": 0.020861,
          "primary_scenario_hit_rate": 0.2,
          "primary_vs_secondary_accuracy_spread": 0.2,
          "sample_gate": "insufficient_samples",
          "secondary_scenario_hit_rate": 0.0
        },
        "20d": {
          "close_call_primary_closer_rate": null,
          "close_call_sample_count": 0,
          "completed_count": 0,
          "primary_closer_than_secondary_rate": null,
          "primary_path_mean_absolute_error": null,
          "primary_path_median_absolute_error": null,
          "primary_scenario_hit_rate": null,
          "primary_vs_secondary_accuracy_spread": null,
          "sample_gate": "insufficient_samples",
          "secondary_scenario_hit_rate": null
        },
        "3d": {
          "close_call_primary_closer_rate": 1.0,
          "close_call_sample_count": 1,
          "completed_count": 5,
          "primary_closer_than_secondary_rate": 0.6,
          "primary_path_mean_absolute_error": 0.013155,
          "primary_path_median_absolute_error": 0.008569,
          "primary_scenario_hit_rate": 0.4,
          "primary_vs_secondary_accuracy_spread": 0.2,
          "sample_gate": "insufficient_samples",
          "secondary_scenario_hit_rate": 0.2
        },
        "5d": {
          "close_call_primary_closer_rate": 0.0,
          "close_call_sample_count": 1,
          "completed_count": 5,
          "primary_closer_than_secondary_rate": 0.4,
          "primary_path_mean_absolute_error": 0.009965,
          "primary_path_median_absolute_error": 0.006769,
          "primary_scenario_hit_rate": 0.2,
          "primary_vs_secondary_accuracy_spread": 0.2,
          "sample_gate": "insufficient_samples",
          "secondary_scenario_hit_rate": 0.0
        },
        "60d": {
          "close_call_primary_closer_rate": null,
          "close_call_sample_count": 0,
          "completed_count": 0,
          "primary_closer_than_secondary_rate": null,
          "primary_path_mean_absolute_error": null,
          "primary_path_median_absolute_error": null,
          "primary_scenario_hit_rate": null,
          "primary_vs_secondary_accuracy_spread": null,
          "sample_gate": "insufficient_samples",
          "secondary_scenario_hit_rate": null
        }
      }
    }
  },
  "core_questions": {
    "edge_vs_no_edge": "insufficient_samples_for_edge_validation",
    "high_confidence_better": "insufficient_samples_for_high_confidence_validation",
    "primary_beats_secondary": "primary_path_more_accurate_than_secondary"
  },
  "current_evidence_level": "early_evidence",
  "generated_at": "2026-06-30T05:19:52.768944+00:00",
  "guardrails": [
    "This scorecard validates probabilistic forecast paths, not trades.",
    "Forecast records are immutable except for future-outcome backfill fields.",
    "Different horizons are scored separately.",
    "If high-confidence buckets do not beat ordinary buckets, model confidence must remain capped."
  ],
  "primary_scenario_accuracy": {
    "10d": {
      "close_call_primary_closer_rate": null,
      "close_call_sample_count": 0,
      "completed_count": 8,
      "primary_closer_than_secondary_rate": 0.75,
      "primary_path_mean_absolute_error": 0.008941,
      "primary_path_median_absolute_error": 0.006645,
      "primary_scenario_hit_rate": 0.25,
      "primary_vs_secondary_accuracy_spread": 0.0,
      "sample_gate": "insufficient_samples",
      "secondary_scenario_hit_rate": 0.25
    },
    "1d": {
      "close_call_primary_closer_rate": 0.5238,
      "close_call_sample_count": 21,
      "completed_count": 44,
      "primary_closer_than_secondary_rate": 0.4773,
      "primary_path_mean_absolute_error": 0.012019,
      "primary_path_median_absolute_error": 0.010246,
      "primary_scenario_hit_rate": 0.3636,
      "primary_vs_secondary_accuracy_spread": 0.0909,
      "sample_gate": "early_evidence",
      "secondary_scenario_hit_rate": 0.2727
    },
    "20d": {
      "close_call_primary_closer_rate": null,
      "close_call_sample_count": 0,
      "completed_count": 0,
      "primary_closer_than_secondary_rate": null,
      "primary_path_mean_absolute_error": null,
      "primary_path_median_absolute_error": null,
      "primary_scenario_hit_rate": null,
      "primary_vs_secondary_accuracy_spread": null,
      "sample_gate": "insufficient_samples",
      "secondary_scenario_hit_rate": null
    },
    "3d": {
      "close_call_primary_closer_rate": 0.6429,
      "close_call_sample_count": 14,
      "completed_count": 36,
      "primary_closer_than_secondary_rate": 0.3611,
      "primary_path_mean_absolute_error": 0.012659,
      "primary_path_median_absolute_error": 0.011191,
      "primary_scenario_hit_rate": 0.25,
      "primary_vs_secondary_accuracy_spread": -0.0833,
      "sample_gate": "early_evidence",
      "secondary_scenario_hit_rate": 0.3333
    },
    "5d": {
      "close_call_primary_closer_rate": 0.8333,
      "close_call_sample_count": 6,
      "completed_count": 28,
      "primary_closer_than_secondary_rate": 0.5714,
      "primary_path_mean_absolute_error": 0.016107,
      "primary_path_median_absolute_error": 0.008924,
      "primary_scenario_hit_rate": 0.3929,
      "primary_vs_secondary_accuracy_spread": 0.25,
      "sample_gate": "early_evidence",
      "secondary_scenario_hit_rate": 0.1429
    },
    "60d": {
      "close_call_primary_closer_rate": null,
      "close_call_sample_count": 0,
      "completed_count": 0,
      "primary_closer_than_secondary_rate": null,
      "primary_path_mean_absolute_error": null,
      "primary_path_median_absolute_error": null,
      "primary_scenario_hit_rate": null,
      "primary_vs_secondary_accuracy_spread": null,
      "sample_gate": "insufficient_samples",
      "secondary_scenario_hit_rate": null
    }
  },
  "sample_counts": {
    "completed_10d": 8,
    "completed_1d": 44,
    "completed_20d": 0,
    "completed_3d": 36,
    "completed_5d": 28,
    "completed_60d": 0,
    "deduped_legacy_rows": 0,
    "pending_forecasts": 48,
    "raw_forecast_rows": 48,
    "total_forecasts": 48
  },
  "sample_gate_rules": {
    "sample_20_50": "early_evidence",
    "sample_50_100": "moderate_evidence",
    "sample_gt_100": "stronger_evidence",
    "sample_lt_20": "insufficient_samples"
  },
  "validation_warning": "Forward validation evidence is accumulating; do not promote models without horizon-specific proof.",
  "version": "forecast_accuracy_scorecard_v1"
}
